openalea/plantconvert/__init__.py
openalea/plantconvert/binary_tools.py
openalea/plantconvert/geometry.py
openalea/plantconvert/material.py
openalea/plantconvert/matrix.py
openalea/plantconvert/plant.py
openalea/plantconvert/util.py
openalea/plantconvert/version.py
openalea/plantconvert/gltf/__init__.py
openalea/plantconvert/gltf/buffer_tools.py
openalea/plantconvert/gltf/reader.py
openalea/plantconvert/gltf/writer.py
openalea/plantconvert/opf/__init__.py
openalea/plantconvert/opf/const.py
openalea/plantconvert/opf/reader.py
openalea/plantconvert/opf/writer.py
openalea/plantconvert/vtk/__init__.py
openalea/plantconvert/vtk/reader.py
openalea/plantconvert/vtk/writer.py
openalea.plantconvert-0.1.0.dist-info/AUTHORS.rst
openalea.plantconvert-0.1.0.dist-info/LICENSE
openalea.plantconvert-0.1.0.dist-info/METADATA
openalea.plantconvert-0.1.0.dist-info/WHEEL
openalea.plantconvert-0.1.0.dist-info/top_level.txt
openalea.plantconvert-0.1.0.dist-info/RECORD
