Metadata-Version: 2.1
Name: openalea.plantconvert
Version: 0.1.0
Summary: Convert a plant to / from a `mtg` format to a wide range of other formats
Author-email: Shenyuan Ma <mashenyuancn@gmail.com>, Christophe Pradal <christophe.pradal@cirad.fr>, Thomas Arsouze <thomas.arsouze@cirad.fr>, Rémi Vézy <remi.vezy@cirad.fr>
License: Apache License
Project-URL: Changelog, https://github.com/thomasarsouze/plantconvert/blob/main/HISTORY.rst
Project-URL: Repository, https://github.com/thomasarsouze/plantconvert
Keywords: MTG,openalea,.opf,format,plantconvert
Classifier: Development Status :: 2 - Pre-Alpha
Classifier: Intended Audience :: Science/Research
Classifier: License :: OSI Approved :: Apache Software License
Classifier: Operating System :: OS Independent
Classifier: Programming Language :: Python
Classifier: Programming Language :: Python :: 3
Classifier: Programming Language :: Python :: 3.9
Classifier: Programming Language :: Python :: 3.10
Classifier: Programming Language :: Python :: 3 :: Only
Classifier: Topic :: Scientific/Engineering
License-File: LICENSE
License-File: AUTHORS.rst
Requires-Dist: numpy >=1.22
Requires-Dist: openalea.mtg >=2.2
Requires-Dist: openalea.plantgl >=3.21
Requires-Dist: vtk >=9.1
Requires-Dist: pygltflib >=1.15
